./.gitignore
./ChessAI.py
./ChessEngine.py
./ChessMain.py
./LICENSE
./PKG-INFO
./README.md
./__init__.py
./generate_sounds.py
./pyproject.toml
./images/bB.png
./images/bK.png
./images/bN.png
./images/bQ.png
./images/bR.png
./images/bp.png
./images/wB.png
./images/wK.png
./images/wN.png
./images/wQ.png
./images/wR.png
./images/wp.png
./sounds/capture.wav
./sounds/castle.wav
./sounds/check.wav
./sounds/game_over.wav
./sounds/move.wav
chessyai-2.0.0.dist-info/METADATA
chessyai-2.0.0.dist-info/WHEEL
chessyai-2.0.0.dist-info/entry_points.txt
chessyai-2.0.0.dist-info/licenses/LICENSE
chessyai-2.0.0.dist-info/RECORD
