Metadata-Version: 2.4
Name: chessyai
Version: 2.0.0
Summary: A fully-featured chess engine with graphical user interface and AI opponent
Project-URL: Homepage, https://github.com/redbasecap/ChessyAI
Project-URL: Repository, https://github.com/redbasecap/ChessyAI
Project-URL: Issues, https://github.com/redbasecap/ChessyAI/issues
Author: redbasecap
License: MIT
License-File: LICENSE
Keywords: ai,chess,game,minimax,pygame
Classifier: Development Status :: 4 - Beta
Classifier: Intended Audience :: End Users/Desktop
Classifier: License :: OSI Approved :: MIT License
Classifier: Operating System :: OS Independent
Classifier: Programming Language :: Python :: 3
Classifier: Programming Language :: Python :: 3.9
Classifier: Programming Language :: Python :: 3.10
Classifier: Programming Language :: Python :: 3.11
Classifier: Programming Language :: Python :: 3.12
Classifier: Topic :: Games/Entertainment :: Board Games
Requires-Python: >=3.9
Requires-Dist: pygame>=2.5.0
